dipper/__init__.py
dipper/config.py
dipper/curie_map.py
dipper/curie_map.yaml
dipper/graph/Graph.py
dipper/graph/RDFGraph.py
dipper/graph/StreamedGraph.py
dipper/graph/__init__.py
dipper/models/Dataset.py
dipper/models/Environment.py
dipper/models/Evidence.py
dipper/models/Family.py
dipper/models/GenomicFeature.py
dipper/models/Genotype.py
dipper/models/Model.py
dipper/models/Pathway.py
dipper/models/Provenance.py
dipper/models/Reference.py
dipper/models/__init__.py
dipper/models/assoc/Association.py
dipper/models/assoc/Chem2DiseaseAssoc.py
dipper/models/assoc/D2PAssoc.py
dipper/models/assoc/DispositionAssoc.py
dipper/models/assoc/G2PAssoc.py
dipper/models/assoc/InteractionAssoc.py
dipper/models/assoc/OrthologyAssoc.py
dipper/models/assoc/__init__.py
dipper/sources/AnimalQTLdb.py
dipper/sources/Bgee.py
dipper/sources/BioGrid.py
dipper/sources/CTD.py
dipper/sources/ClinVar.py
dipper/sources/ClinVarXML_alpha.py
dipper/sources/Coriell.py
dipper/sources/Decipher.py
dipper/sources/EOM.py
dipper/sources/Ensembl.py
dipper/sources/FlyBase.py
dipper/sources/GWASCatalog.py
dipper/sources/GeneOntology.py
dipper/sources/GeneReviews.py
dipper/sources/HGNC.py
dipper/sources/HPOAnnotations.py
dipper/sources/IMPC.py
dipper/sources/KEGG.py
dipper/sources/MGI.py
dipper/sources/MGISlim.py
dipper/sources/MMRRC.py
dipper/sources/MPD.py
dipper/sources/Monarch.py
dipper/sources/Monochrom.py
dipper/sources/MyDrug.py
dipper/sources/NCBIGene.py
dipper/sources/OMIA.py
dipper/sources/OMIM.py
dipper/sources/Orphanet.py
dipper/sources/Panther.py
dipper/sources/PostgreSQLSource.py
dipper/sources/Reactome.py
dipper/sources/Source.py
dipper/sources/StringDB.py
dipper/sources/UCSCBands.py
dipper/sources/UDP.py
dipper/sources/WormBase.py
dipper/sources/ZFIN.py
dipper/sources/ZFINSlim.py
dipper/sources/__init__.py
dipper/utils/CurieUtil.py
dipper/utils/DipperUtil.py
dipper/utils/GraphUtils.py
dipper/utils/TestUtils.py
dipper-0.1.3.dist-info/DESCRIPTION.rst
dipper-0.1.3.dist-info/METADATA
dipper-0.1.3.dist-info/RECORD
dipper-0.1.3.dist-info/WHEEL
dipper-0.1.3.dist-info/metadata.json
dipper-0.1.3.dist-info/top_level.txt
