Metadata-Version: 2.0
Name: dipper
Version: 0.1.3
Summary: Library for transforming data from open genomic databases to RDF
Home-page: https://github.com/monarch-initiative/dipper
Author: Kent Shefchek
Author-email: kshefchek@gmail.com
License: BSD
Keywords: ontology graph obo owl sparql rdf
Platform: UNKNOWN
Classifier: Intended Audience :: Science/Research
Classifier: Topic :: Scientific/Engineering :: Bio-Informatics
Classifier: Topic :: Scientific/Engineering :: Information Analysis
Classifier: License :: OSI Approved :: BSD License
Classifier: Programming Language :: Python :: 3
Classifier: Topic :: Scientific/Engineering :: Visualization
Requires-Dist: psycopg2
Requires-Dist: rdflib
Requires-Dist: isodate
Requires-Dist: roman
Requires-Dist: python-docx
Requires-Dist: pyyaml
Requires-Dist: pysftp
Requires-Dist: beautifulsoup4
Requires-Dist: GitPython
Requires-Dist: intermine
Requires-Dist: pandas
